curifactory/__init__.py
curifactory/caching.py
curifactory/cli.py
curifactory/dag.py
curifactory/docker.py
curifactory/experiment.py
curifactory/hashing.py
curifactory/manager.py
curifactory/notebook.py
curifactory/params.py
curifactory/procedure.py
curifactory/project.py
curifactory/record.py
curifactory/reporting.py
curifactory/staging.py
curifactory/store.py
curifactory/utils.py
curifactory/data/.dockerignore
curifactory/data/debug.py
curifactory/data/dockerfile
curifactory/data/startup.sh
curifactory/data/style.css
curifactory-0.20.0.dist-info/licenses/LICENSE
curifactory-0.20.0.dist-info/METADATA
curifactory-0.20.0.dist-info/WHEEL
curifactory-0.20.0.dist-info/entry_points.txt
curifactory-0.20.0.dist-info/top_level.txt
curifactory-0.20.0.dist-info/RECORD
