Metadata-Version: 2.4
Name: curifactory
Version: 0.20.0
Summary: An experiment workflow and organization tool
Author-email: "Nathan Martindale, Jason Hite, Scott L. Stewart, Mark Adams" <curifactory-help@ornl.gov>
License-Expression: BSD-3-Clause
Project-URL: Repository, https://github.com/ORNL/curifactory
Project-URL: Changelog, https://github.com/ORNL/curifactory/blob/main/CHANGELOG.md
Project-URL: Issues, https://github.com/ORNL/curifactory/issues
Project-URL: Documentation, https://ornl.github.io/curifactory/stable/index.html
Keywords: research,experiment,workflow
Classifier: Programming Language :: Python :: 3
Classifier: Programming Language :: Python :: 3.10
Classifier: Programming Language :: Python :: 3.11
Classifier: Programming Language :: Python :: 3.12
Classifier: Programming Language :: Python :: 3.13
Classifier: Programming Language :: Python :: 3.14
Classifier: Operating System :: OS Independent
Classifier: Development Status :: 4 - Beta
Classifier: Environment :: Console
Classifier: Intended Audience :: Science/Research
Requires-Python: >=3.10
License-File: LICENSE
Requires-Dist: numpy
Requires-Dist: pandas
Requires-Dist: ipynb-py-convert
Requires-Dist: graphviz
Requires-Dist: matplotlib
Requires-Dist: psutil
Requires-Dist: rich
Requires-Dist: argcomplete
Requires-Dist: duckdb
Provides-Extra: h5
Requires-Dist: tables; extra == "h5"
Dynamic: license-file
